DuSC_explorer/__init__.py
DuSC_explorer/minimum_gui.py
dusc_explorer-1.1.4.dist-info/licenses/LICENSE
dusc_explorer-1.1.4.dist-info/METADATA
dusc_explorer-1.1.4.dist-info/WHEEL
dusc_explorer-1.1.4.dist-info/entry_points.txt
dusc_explorer-1.1.4.dist-info/top_level.txt
dusc_explorer-1.1.4.dist-info/RECORD
