Metadata-Version: 2.4
Name: DuSC_explorer
Version: 1.1.4
Summary: Graphical user interface to view Dual Space Crystallography data from the 4D Camera of the Molecular Foundry.
Author-email: Peter Ercius <percius@lbl.gov>
Requires-Python: >=3.8
License-File: LICENSE
Requires-Dist: stempy>=3.0
Requires-Dist: pyqtgraph>=0.13
Requires-Dist: tifffile
Requires-Dist: h5py>=2.9.0
Requires-Dist: numpy
Requires-Dist: qtpy
Requires-Dist: numba>=0.56
Requires-Dist: PyQt5
Dynamic: license-file
